InstaReq/__init__.py
InstaReq/__main__.py
InstaReq/instareq.py
InstaReq-0.1.2.dist-info/LICENSE
InstaReq-0.1.2.dist-info/METADATA
InstaReq-0.1.2.dist-info/WHEEL
InstaReq-0.1.2.dist-info/entry_points.txt
InstaReq-0.1.2.dist-info/top_level.txt
InstaReq-0.1.2.dist-info/RECORD
